{
  "generatedAt": "2026-05-11T19:24:04.993Z",
  "registryIndexedAt": "2026-05-11T19:23:38.307Z",
  "network": "livenet",
  "btcUsd": 80891.51,
  "model": {
    "name": "ProofOfWork.Me Mail App Value Model",
    "formula": "annual_flow_sats = directed_pairs * edge_density * messages_per_pair_per_year * sats_per_delivery; network_value_sats = annual_flow_sats * flow_multiple",
    "note": "This values the mail app as paid attention flow across the PowID graph. It is a model, not a guaranteed market price."
  },
  "current": {
    "confirmedPowIds": 94,
    "uniqueReceiveAddresses": 26,
    "directedIdPairs": 8742,
    "directedAddressPairs": 650,
    "uniqueProtocolTxids": 12,
    "uniqueProtocolEdges": 15,
    "powAddressToPowAddressEdges": 12,
    "uniquePowAddressDirectedPairs": 8,
    "powAddressPairDensity": 0.012307692307692308,
    "totalProtocolEdgeSats": 10202,
    "totalProtocolEdgeBtc": 0.00010202,
    "totalProtocolEdgeUsd": 8.2525518502,
    "averageSatsPerDelivery": 680.1333333333333,
    "medianSatsPerDelivery": 546,
    "uniqueSenderAddresses": 3,
    "uniqueRecipientAddresses": 7,
    "inboxTxids": 12,
    "sentTxids": 12,
    "attachmentTxids": 4,
    "replyTxids": 5,
    "multiRecipientTxids": 1,
    "firstMailAt": "2026-05-07T07:20:57.000Z",
    "mailAgeDays": 4.501866979166667,
    "currentFlowSatsPerDay": 2266.170912470736,
    "annualizedCurrentFlowSats": 827152.3830518186,
    "annualizedCurrentFlowBtc": 0.008271523830518187,
    "annualizedCurrentFlowUsd": 669.0960526516002
  },
  "scenarios": [
    {
      "scenario": "conservative",
      "edgeDensity": 0.005,
      "messagesPerPairPerYear": 1,
      "satsPerDelivery": 546,
      "flowMultiple": 5
    },
    {
      "scenario": "base_current_density",
      "edgeDensity": 0.012307692307692308,
      "messagesPerPairPerYear": 4,
      "satsPerDelivery": 680.1333333333333,
      "flowMultiple": 5
    },
    {
      "scenario": "paid_inbox_monthly",
      "edgeDensity": 0.05,
      "messagesPerPairPerYear": 12,
      "satsPerDelivery": 1000,
      "flowMultiple": 5
    }
  ],
  "headline24MonthNetworkValueUsd": {
    "recentPaceConservative": 1014107.25,
    "recentPaceBaseCurrentDensity": 12438039.22,
    "recentPacePaidInboxMonthly": 222880714.01,
    "launchAverageConservative": 3744982.46,
    "launchAverageBaseCurrentDensity": 45932260.9,
    "launchAveragePaidInboxMonthly": 823073068.59
  }
}
